{"ts":"2026-05-30 15:30","mkt":{"network":20.27,"yield":0.0944,"price":1.1335,"pool":null},"fx":6.781722,"fx_src":"er-api","price":1.1335,"total":{"income_h_prl":0.7819,"income_h_cny":6.0105293274453,"cost_h_cny":5.9,"net_h_cny":0.11052932744529986,"cum_prl":93.31438837,"cum_cny":717.3153446355105,"a100_cost_known":false},"wallets":[{"name":"3090","res":"1× RTX 3090","cards":1,"cost_h":1.5,"cls":"consumer","pool":"alphapool","online":true,"estHash1h":85.49805589648103,"estHash24h":28.398415802849286,"baseline":45,"recover_pct":33.2,"hourly":[{"ts":1780110000,"prl":0.2261,"pending":false,"price":1.1412},{"ts":1780113600,"prl":0.3853,"pending":false,"price":1.1556},{"ts":1780117200,"prl":0.4441,"pending":false,"price":1.1095},{"ts":1780120800,"prl":0.3328,"pending":false,"price":0.9957},{"ts":1780124400,"prl":0.1191,"pending":false,"price":1.1335}],"cum":2.42082481,"migrated":"2026-05-30 00:39","last_hour_prl":0.1191},{"name":"4090","res":"1× RTX 4090","cards":1,"cost_h":2.0,"cls":"consumer","pool":"alphapool","online":true,"estHash1h":150.52741457126098,"estHash24h":54.57054877281236,"baseline":92,"recover_pct":36.3,"hourly":[{"ts":1780110000,"prl":0.4161,"pending":false,"price":1.1412},{"ts":1780113600,"prl":0.7013,"pending":false,"price":1.1556},{"ts":1780117200,"prl":0.8585,"pending":false,"price":1.1095},{"ts":1780120800,"prl":0.6556,"pending":false,"price":0.9957},{"ts":1780124400,"prl":0.2196,"pending":false,"price":1.1335}],"cum":4.69268944,"migrated":"2026-05-30 05:25","last_hour_prl":0.2196},{"name":"5090","res":"1× RTX 5090","cards":1,"cost_h":2.4,"cls":"consumer","pool":"alphapool","online":true,"estHash1h":253.6528517175283,"estHash24h":119.88830262568631,"baseline":175,"recover_pct":47.3,"hourly":[{"ts":1780095600,"prl":1.8407,"pending":false,"price":1.3085},{"ts":1780110000,"prl":0.9521,"pending":false,"price":1.1412},{"ts":1780113600,"prl":1.6789,"pending":false,"price":1.1556},{"ts":1780117200,"prl":1.9464,"pending":false,"price":1.1095},{"ts":1780120800,"prl":1.3337,"pending":false,"price":0.9957},{"ts":1780124400,"prl":0.4432,"pending":false,"price":1.1335}],"cum":10.4218039,"migrated":"2026-05-30 05:26","last_hour_prl":0.4432},{"name":"a100-96","res":"8× A100-40G","cards":8,"cost_h":0.0,"cls":"a100","pool":"alphapool","online":false,"estHash1h":0.0,"estHash24h":423.04646499697856,"baseline":960,"recover_pct":0,"hourly":[{"ts":1780084800,"prl":5.3269,"pending":false,"price":1.5208},{"ts":1780095600,"prl":13.359,"pending":false,"price":1.3085},{"ts":1780110000,"prl":3.0034,"pending":false,"price":1.1412},{"ts":1780113600,"prl":4.802,"pending":false,"price":1.1556},{"ts":1780117200,"prl":2.9754,"pending":false,"price":1.1095},{"ts":1780120800,"prl":1.1388,"pending":false,"price":0.9957},{"ts":1780124400,"prl":0.2453,"pending":false,"price":1.1335}],"cum":38.25893684,"last_hour_prl":0.2453},{"name":"a100-103","res":"8× A100-40G","cards":8,"cost_h":0.0,"cls":"a100","pool":"alphapool","online":false,"estHash1h":0.0,"estHash24h":414.6087313201198,"baseline":960,"recover_pct":0,"hourly":[{"ts":1780084800,"prl":5.1099,"pending":false,"price":1.5208},{"ts":1780095600,"prl":13.2299,"pending":false,"price":1.3085},{"ts":1780110000,"prl":2.9618,"pending":false,"price":1.1412},{"ts":1780113600,"prl":4.6575,"pending":false,"price":1.1556},{"ts":1780117200,"prl":2.8766,"pending":false,"price":1.1095},{"ts":1780120800,"prl":1.101,"pending":false,"price":0.9957},{"ts":1780124400,"prl":0.2371,"pending":false,"price":1.1335}],"cum":37.520133380000004,"last_hour_prl":0.2371}]}